Metadata-Version: 2.1
Name: tsfuse
Version: 0.2.3
Summary: Automated feature construction for multiple time series data
Author: Arne De Brabandere
Requires-Python: >=3.10,<3.11
Classifier: Programming Language :: Python :: 3
Classifier: Programming Language :: Python :: 3.10
Requires-Dist: cython (>=3.0.5,<4.0.0)
Requires-Dist: graphviz (>=0.20.1,<0.21.0)
Requires-Dist: matplotlib (>=3.10.0,<4.0.0)
Requires-Dist: numpy (>=1.26.4,<2.0.0)
Requires-Dist: pandas (>=1.5.3,<2.0.0)
Requires-Dist: pint (>=0.21.1,<0.22.0)
Requires-Dist: pytest (>=7.4.3,<8.0.0)
Requires-Dist: scikit-learn (>=1.3.2,<2.0.0)
Requires-Dist: scipy (>=1.14.0,<2.0.0)
Requires-Dist: setuptools (>=70.0.0,<71.0.0)
Requires-Dist: six (>=1.16.0,<2.0.0)
Requires-Dist: sktime (>=0.23.1,<0.24.0)
Requires-Dist: statsmodels (>=0.14.0,<0.15.0)
Requires-Dist: tselect (>=0.1.1,<0.2.0)
